mutwo/core_constants/__init__.py
mutwo/core_converters/__init__.py
mutwo/core_converters/abc.py
mutwo/core_converters/configurations.py
mutwo/core_converters/parsers.py
mutwo/core_converters/tempos.py
mutwo/core_events/__init__.py
mutwo/core_events/abc.py
mutwo/core_events/basic.py
mutwo/core_events/configurations.py
mutwo/core_events/envelopes.py
mutwo/core_generators/__init__.py
mutwo/core_generators/generic.py
mutwo/core_parameters/__init__.py
mutwo/core_parameters/abc.py
mutwo/core_parameters/configurations.py
mutwo/core_parameters/durations.py
mutwo/core_parameters/tempos.py
mutwo/core_utilities/__init__.py
mutwo/core_utilities/configurations.py
mutwo/core_utilities/decorators.py
mutwo/core_utilities/exceptions.py
mutwo/core_utilities/prime_factors.py
mutwo/core_utilities/tools.py
mutwo/core_version/__init__.py
mutwo.ext_core-0.61.1.dist-info/LICENSE
mutwo.ext_core-0.61.1.dist-info/METADATA
mutwo.ext_core-0.61.1.dist-info/WHEEL
mutwo.ext_core-0.61.1.dist-info/top_level.txt
mutwo.ext_core-0.61.1.dist-info/RECORD
