Metadata-Version: 2.1
Name: mutwo.ext-core
Version: 0.61.1
Summary: core library for event based framework mutwo
Home-page: https://github.com/mutwo-org/mutwo
Author: Tim Pauli,  Levin Eric Zimmermann
Author-email: tim.pauli@folkwang-uni.de, levin.eric.zimmermann@posteo.eu
License: GPL
Project-URL: Documentation, https://mutwo.readthedocs.io/en/latest/
Requires-Python: >=3.9, <4
License-File: LICENSE
Requires-Dist: primesieve (<3.0.0,>=2.0.0)
Requires-Dist: numpy (<2.00,>=1.18)
Requires-Dist: scipy (<2.0.0,>=1.4.1)
Requires-Dist: python-ranges (<1.0.0,>=0.2.0)
Provides-Extra: testing
Requires-Dist: nose ; extra == 'testing'
